cognify/None.py
cognify/__init__.py
cognify/_nbdev.py
cognify/analysis.py
cognify/api.py
cognify/cognitive.py
cognify/core.py
cognify/dataset.py
cognify/dataset_prisma.py
cognify/heartrate.py
cognify/metric.py
cognify/model.py
cognify/muse.py
cognify/optoceutics.py
cognify/preprocess.py
cognify/report.py
cognify/simulate.py
cognify/spectra.py
cognify/summary.py
cognify/test.py
cognify-0.0.11.dist-info/LICENSE
cognify-0.0.11.dist-info/METADATA
cognify-0.0.11.dist-info/WHEEL
cognify-0.0.11.dist-info/entry_points.txt
cognify-0.0.11.dist-info/top_level.txt
cognify-0.0.11.dist-info/RECORD
